nba_summer_league_headshots/NBA_Roster_Clean.csv
nba_summer_league_headshots/__init__.py
nba_summer_league_headshots/api.py
nba_summer_league_headshots/cli.py
nba_summer_league_headshots/NBA_Combined_Headshots/AJ_Hoggard.jpg
nba_summer_league_headshots/NBA_Combined_Headshots/AJ_Johnson.png
nba_summer_league_headshots/NBA_Combined_Headshots/AJ_Lawson.png
nba_summer_league_headshots/NBA_Combined_Headshots/Aaron_Estrada.jpg
nba_summer_league_headshots/NBA_Combined_Headshots/Aaron_Scott.png
nba_summer_league_headshots/NBA_Combined_Headshots/Ace_Bailey.png
nba_summer_league_headshots/NBA_Combined_Headshots/Ace_Baldwin_Jr.jpg
nba_summer_league_headshots/NBA_Combined_Headshots/Adam_Flagler.png
nba_summer_league_headshots/NBA_Combined_Headshots/Adama_Sanogo.png
nba_summer_league_headshots/NBA_Combined_Headshots/Adem_Bona.png
nba_summer_league_headshots/NBA_Combined_Headshots/Adonis_Arms.jpg
nba_summer_league_headshots/NBA_Combined_Headshots/Ajay_Mitchell.png
nba_summer_league_headshots/NBA_Combined_Headshots/Akoldah_Gak.jpg
nba_summer_league_headshots/NBA_Combined_Headshots/Alex_Ducas.png
nba_summer_league_headshots/NBA_Combined_Headshots/Alex_Higgins_Titsha.png
nba_summer_league_headshots/NBA_Combined_Headshots/Alex_Reese.png
nba_summer_league_headshots/NBA_Combined_Headshots/Alex_Sarr.png
nba_summer_league_headshots/NBA_Combined_Headshots/Alex_Schumacher.jpg
nba_summer_league_headshots/NBA_Combined_Headshots/Alex_Toohey.png
nba_summer_league_headshots/NBA_Combined_Headshots/Alijah_Martin.png
nba_summer_league_headshots/NBA_Combined_Headshots/Aliou_Diarra.jpg
nba_summer_league_headshots/NBA_Combined_Headshots/Alondes_Williams.png
nba_summer_league_headshots/NBA_Combined_Headshots/Amari_Bailey.png
nba_summer_league_headshots/NBA_Combined_Headshots/Amari_Williams.png
nba_summer_league_headshots/NBA_Combined_Headshots/Andre_Jackson_Jr.png
nba_summer_league_headshots/NBA_Combined_Headshots/Andrew_Carr.png
nba_summer_league_headshots/NBA_Combined_Headshots/Andrew_Funk.png
nba_summer_league_headshots-1.0.2.dist-info/licenses/LICENSE
nba_summer_league_headshots-1.0.2.dist-info/METADATA
nba_summer_league_headshots-1.0.2.dist-info/WHEEL
nba_summer_league_headshots-1.0.2.dist-info/entry_points.txt
nba_summer_league_headshots-1.0.2.dist-info/top_level.txt
nba_summer_league_headshots-1.0.2.dist-info/RECORD
