Metadata-Version: 2.4
Name: nba-summer-league-headshots
Version: 1.0.2
Summary: NBA Summer League 2025 Player Headshots API - Access 431+ verified player images
Home-page: https://github.com/BuddyBob/summer_league_headshot_api
Author: Thavas Antonio
Author-email: Thavas Antonio <thavasantonio@gmail.com>
License: MIT
Project-URL: Homepage, https://github.com/BuddyBob/summer_league_headshot_api
Project-URL: Bug Reports, https://github.com/BuddyBob/summer_league_headshot_api/issues
Project-URL: Source, https://github.com/BuddyBob/summer_league_headshot_api
Keywords: nba,basketball,headshots,summer league,sports,api
Classifier: Development Status :: 4 - Beta
Classifier: Intended Audience :: Developers
Classifier: Topic :: Software Development :: Libraries :: Python Modules
Classifier: License :: OSI Approved :: MIT License
Classifier: Programming Language :: Python :: 3
Classifier: Programming Language :: Python :: 3.8
Classifier: Programming Language :: Python :: 3.9
Classifier: Programming Language :: Python :: 3.10
Classifier: Programming Language :: Python :: 3.11
Classifier: Programming Language :: Python :: 3.12
Requires-Python: >=3.8
License-File: LICENSE
Dynamic: author
Dynamic: home-page
Dynamic: license-file
Dynamic: requires-python
